{
  "updated_at": "2026-07-24T09:00:26-03:00",
  "source": "CEPEA/Esalq",
  "source_url": "https://www.cepea.org.br/",
  "items": [
    {
      "name": "Boi Gordo",
      "slug": "boi-gordo",
      "icon": "boi",
      "unit": "@",
      "value": 343.75,
      "value_display": "R$ 343,75",
      "date": "2026-07-23"
    },
    {
      "name": "Bezerro - MS",
      "slug": "bezerro-ms",
      "icon": "",
      "unit": "cabeça",
      "value": 3395.4,
      "value_display": "R$ 3.395,40",
      "date": "2026-07-23"
    },
    {
      "name": "Bezerro - SP",
      "slug": "bezerro-sp",
      "icon": "",
      "unit": "cabeça",
      "value": 3164.71,
      "value_display": "R$ 3.164,71",
      "date": "2026-07-23"
    },
    {
      "name": "Soja - PR",
      "slug": "soja-pr",
      "icon": "soja",
      "unit": "sc de 60kg",
      "value": 139.28,
      "value_display": "R$ 139,28",
      "date": "2026-07-23"
    },
    {
      "name": "Milho",
      "slug": "milho",
      "icon": "milho",
      "unit": "sc de 60kg",
      "value": 65.55,
      "value_display": "R$ 65,55",
      "date": "2026-07-23"
    },
    {
      "name": "Trigo - PR",
      "slug": "trigo-pr",
      "icon": "",
      "unit": "t",
      "value": 1394.69,
      "value_display": "R$ 1.394,69",
      "date": "2026-07-23"
    },
    {
      "name": "Trigo - RS",
      "slug": "trigo-rs",
      "icon": "",
      "unit": "t",
      "value": 1321.59,
      "value_display": "R$ 1.321,59",
      "date": "2026-07-23"
    },
    {
      "name": "Café Arábica",
      "slug": "cafe-arabica",
      "icon": "cafe",
      "unit": "sc de 60kg",
      "value": 1692.59,
      "value_display": "R$ 1.692,59",
      "date": "2026-07-23"
    },
    {
      "name": "Café Robusta",
      "slug": "caf-robusta",
      "icon": "",
      "unit": "sc de 60kg",
      "value": 1066.24,
      "value_display": "R$ 1.066,24",
      "date": "2026-07-23"
    },
    {
      "name": "ARROZ EM CASCA CEPEA/IRGA-RS (58% DE GRÃOS INTEIROS)",
      "slug": "arroz-em-casca-cepea-irga-rs-58-de-gr-os-inteiros",
      "icon": "",
      "unit": "sc de 50kg",
      "value": 66.72,
      "value_display": "R$ 66,72",
      "date": "2026-07-23"
    },
    {
      "name": "Açúcar - SP",
      "slug": "a-car-sp",
      "icon": "",
      "unit": "sc de 50kg",
      "value": 91.49,
      "value_display": "R$ 91,49",
      "date": "2026-07-23"
    },
    {
      "name": "Açúcar - Santos",
      "slug": "a-car-santos",
      "icon": "",
      "unit": "sc de 50kg",
      "value": 105.9,
      "value_display": "R$ 105,90",
      "date": "2026-07-23"
    },
    {
      "name": "Etanol Anidro - AL",
      "slug": "etanol-anidro-al",
      "icon": "",
      "unit": "litro",
      "value": 3.0634,
      "value_display": "R$ 3,0634",
      "date": "2026-05-15"
    },
    {
      "name": "Etanol Anidro - MT",
      "slug": "etanol-anidro-mt",
      "icon": "",
      "unit": "m3",
      "value": 2685.79,
      "value_display": "R$ 2.685,79",
      "date": "2026-05-22"
    },
    {
      "name": "Etanol Anidro - PB",
      "slug": "etanol-anidro-pb",
      "icon": "",
      "unit": "litro",
      "value": 3.2115,
      "value_display": "R$ 3,2115",
      "date": "2026-07-03"
    },
    {
      "name": "Etanol Anidro - PE",
      "slug": "etanol-anidro-pe",
      "icon": "",
      "unit": "litro",
      "value": 3.2894,
      "value_display": "R$ 3,2894",
      "date": "2026-05-08"
    },
    {
      "name": "Etanol Anidro - SP",
      "slug": "etanol-anidro-sp",
      "icon": "",
      "unit": "litro",
      "value": 2.4421,
      "value_display": "R$ 2,4421",
      "date": "2026-07-17"
    },
    {
      "name": "Etanol Hidratado - AL",
      "slug": "etanol-hidratado-al",
      "icon": "",
      "unit": "litro",
      "value": 2.7942,
      "value_display": "R$ 2,7942",
      "date": "2026-05-22"
    },
    {
      "name": "Etanol Hidratado - GO",
      "slug": "etanol-hidratado-go",
      "icon": "",
      "unit": "litro",
      "value": 2.4044,
      "value_display": "R$ 2,4044",
      "date": "2026-07-17"
    },
    {
      "name": "Etanol Hidratado - MT",
      "slug": "etanol-hidratado-mt",
      "icon": "",
      "unit": "m3",
      "value": 2652.81,
      "value_display": "R$ 2.652,81",
      "date": "2026-07-17"
    },
    {
      "name": "Etanol Hidratado - PE",
      "slug": "etanol-hidratado-pe",
      "icon": "",
      "unit": "litro",
      "value": 3.164,
      "value_display": "R$ 3,164",
      "date": "2026-05-08"
    },
    {
      "name": "Etanol Hidratado - SP",
      "slug": "etanol-hidratado-sp",
      "icon": "",
      "unit": "litro",
      "value": 2.1336,
      "value_display": "R$ 2,1336",
      "date": "2026-07-17"
    }
  ]
}