{
  "updated_at": "2026-07-15T14:30:41-03:00",
  "source": "CEPEA/Esalq",
  "source_url": "https://www.cepea.org.br/",
  "items": [
    {
      "name": "Boi Gordo",
      "slug": "boi-gordo",
      "icon": "boi",
      "unit": "@",
      "value": 328.1,
      "value_display": "R$ 328,10",
      "date": "2026-07-14"
    },
    {
      "name": "Soja - PR",
      "slug": "soja-pr",
      "icon": "soja",
      "unit": "sc de 60kg",
      "value": 132.94,
      "value_display": "R$ 132,94",
      "date": "2026-07-14"
    },
    {
      "name": "Milho",
      "slug": "milho",
      "icon": "milho",
      "unit": "sc de 60kg",
      "value": 64.64,
      "value_display": "R$ 64,64",
      "date": "2026-07-14"
    },
    {
      "name": "Café Arábica",
      "slug": "cafe-arabica",
      "icon": "cafe",
      "unit": "sc de 60kg",
      "value": 1755.35,
      "value_display": "R$ 1.755,35",
      "date": "2026-07-14"
    }
  ]
}